aioscrapper/__init__.py
aioscrapper/config.py
aioscrapper/exceptions.py
aioscrapper/helpers.py
aioscrapper/pipeline/__init__.py
aioscrapper/pipeline/base.py
aioscrapper/pipeline/dispatcher.py
aioscrapper/scrapper/__init__.py
aioscrapper/scrapper/base.py
aioscrapper/scrapper/executor.py
aioscrapper/scrapper/request_manager.py
aioscrapper/session/__init__.py
aioscrapper/session/aiohttp.py
aioscrapper/session/base.py
aioscrapper/types/__init__.py
aioscrapper/types/middleware.py
aioscrapper/types/pipeline.py
aioscrapper/types/session.py
aioscrapper-0.2.0.dist-info/licenses/LICENSE
aioscrapper-0.2.0.dist-info/METADATA
aioscrapper-0.2.0.dist-info/WHEEL
aioscrapper-0.2.0.dist-info/top_level.txt
aioscrapper-0.2.0.dist-info/RECORD
