Metadata-Version: 2.4
Name: aioscrapper
Version: 0.2.0
Summary: Async framework for building modular and scalable web scrapers.
Author: darkstussy
Project-URL: Homepage, https://github.com/darkstussy/aioscrapper
Project-URL: Issues, https://github.com/darkstussy/aioscrapper/issues
Classifier: Programming Language :: Python :: 3
Classifier: Programming Language :: Python :: 3.12
Classifier: Framework :: AsyncIO
Classifier: Intended Audience :: Developers
Classifier: Operating System :: OS Independent
Classifier: Topic :: Internet :: WWW/HTTP :: Indexing/Search
Classifier: Topic :: Software Development :: Libraries :: Application Frameworks
Requires-Python: >=3.10
License-File: LICENSE
Requires-Dist: aiohttp[speedups]~=3.11.16
Requires-Dist: aiojobs~=1.4.0
Provides-Extra: dev
Requires-Dist: flake8~=7.1.2; extra == "dev"
Requires-Dist: black~=25.1.0; extra == "dev"
Requires-Dist: pyright~=1.1.399; extra == "dev"
Requires-Dist: aiohttp[speedups]~=3.11.16; extra == "dev"
Requires-Dist: aiojobs~=1.4.0; extra == "dev"
Provides-Extra: test
Requires-Dist: pytest~=8.3.5; extra == "test"
Requires-Dist: pytest-asyncio~=0.26.0; extra == "test"
Requires-Dist: aresponses~=3.0.0; extra == "test"
Dynamic: license-file
